LICENSE
MANIFEST.in
README.rst
backport_abcoll.py
backport_collections.py
mapping_tests.py
seq_tests.py
setup.cfg
setup.py
test_collections.py
test_deque.py
test_support.py
backport_collections.egg-info/PKG-INFO
backport_collections.egg-info/SOURCES.txt
backport_collections.egg-info/dependency_links.txt
backport_collections.egg-info/top_level.txt
backport_collections.egg-info/zip-safe