Metadata-Version: 1.1
Name: backport-collections
Version: 0.1
Summary: Backport of Python 2.7's collections module
Home-page: http://github.com/sk-/backport_collections
Author: Sebastian Kreft
Author-email: UNKNOWN
License: UNKNOWN
Platform: UNKNOWN
Classifier: Development Status :: 5 - Production/Stable
Classifier: Intended Audience :: Developers
Classifier: License :: OSI Approved :: Python Software Foundation License
Classifier: Programming Language :: Python :: 2.6
